[
  {
    "id": 0,
    "additionalInfo": {
      "languages": [
        "es"
      ]
    },
    "displayName": "API - Asistencia a evento en UC3M",
    "label": "",
    "defaultLanguage": "es",
    "title": {
      "contents": [
        {
          "content": "API - Asistencia a evento en UC3M",
          "language": "es",
          "format": "text/plain"
        }
      ]
    },
    "description": {
      "contents": [
        {
          "content": "API - Asistencia a evento CertiDigital patrocinado por UC3M",
          "language": "es",
          "format": "text/plain"
        }
      ],
      "topic": ""
    },
    "type": {
      "uri": "",
      "targetName": {
        "contents": [
          {
            "content": "Generic",
            "language": "es",
            "format": "text/plain"
          }
        ]
      },
      "targetDescription": null,
      "targetFrameworkURI": "",
      "targetNotation": null,
      "targetFramework": null
    },
    "validFrom": "2024-03-06T23:00:00Z",
    "validUntil": null,
    "identifier": [],
    "relAchieved": {
      "oid": [],
      "singleOid": null
    },
    "relPerformed": {
      "oid": [],
      "singleOid": null
    },
    "relEntitledTo": {
      "oid": [],
      "singleOid": null
    },
    "relIssuer": {
      "oid": [],
      "singleOid": null
    },
    "relDiploma": {
      "oid": [],
      "singleOid": null
    }
  }
]